recontact/__init__.py
recontact/apps.py
recontact/forms.py
recontact/urls.py
recontact/views.py
recontact/templates/recontact/base.html
recontact/templates/recontact/contact.html
recontact/templates/recontact/index.html
recontact/templates/recontact/message_sent.html
django_recontact-0.4.dist-info/LICENSE.txt
django_recontact-0.4.dist-info/METADATA
django_recontact-0.4.dist-info/WHEEL
django_recontact-0.4.dist-info/top_level.txt
django_recontact-0.4.dist-info/RECORD
