Metadata-Version: 2.1
Name: django-recontact
Version: 0.4
Summary: Django contact application with invisible recaptcha
Home-page: https://bitbucket.org/marc_culler/recontact
Author: Marc Culler
Author-email: mcbugs000@gmail.com
License: GPL
Keywords: django contact recaptcha
Platform: UNKNOWN
Classifier: Development Status :: 4 - Beta
Classifier: Intended Audience :: Developers
Classifier: Topic :: Software Development
Classifier: Framework :: Django
Classifier: License :: OSI Approved :: GNU General Public License v2 or later (GPLv2+)
Classifier: Programming Language :: Python :: 3.5
Classifier: Programming Language :: Python :: 3.6
Requires-Dist: django
